feature_center/__init__.py
feature_center/downloader/__init__.py
feature_center/downloader/downloader.py
feature_center-0.2.dist-info/LICENSE
feature_center-0.2.dist-info/METADATA
feature_center-0.2.dist-info/WHEEL
feature_center-0.2.dist-info/top_level.txt
feature_center-0.2.dist-info/RECORD
